daiolog/__init__.py
daiolog/decorators.py
daiolog/formatters.py
daiolog/handler.py
daiolog/json_encoder.py
daiolog/listener.py
daiolog-1.1.1.dist-info/METADATA
daiolog-1.1.1.dist-info/WHEEL
daiolog-1.1.1.dist-info/RECORD
