Metadata-Version: 2.1
Name: daiolog
Version: 1.1.1
Summary: JSON logging in a separate thread for asyncio projects
Home-page: https://github.com/anysoft-kz/daiolog
Author: Vladislav Vorobyov
Author-email: vladislav.vorobyov@gmail.com
Requires-Python: >=3.9,<4.0
Classifier: Programming Language :: Python :: 3
Classifier: Programming Language :: Python :: 3.9
Classifier: Programming Language :: Python :: 3.10
Classifier: Programming Language :: Python :: 3.11
Classifier: Programming Language :: Python :: 3.12
Project-URL: Repository, https://github.com/anysoft-kz/daiolog
